{
  "component": "Sidepane / Panel",
  "description": "Slide-in overlay panel that slides from the right edge. Supports two independent layers (Layer 1 = primary content, Layer 2 = drill-down sub-view that slides over Layer 1). Implemented in ZASidePane.js.",
  "codebasePath": "zohoanalyticsclient/src/js/component/sidepane/ZASidePane.js",
  "cssClass": "newUiDialog sidepane za-sidepanel-dialog",
  "figmaPage": "🟠 - Components",
  "figmaNodeId": "5015:11997",

  "variants": {
    "Layer": ["Layer1", "Layer2"],
    "ShowFooter": ["Yes", "No"]
  },

  "componentPropertyDefinitions": {
    "Layer": {
      "type": "VARIANT",
      "description": "Layer1 = primary pane. Layer2 = secondary/drill-down pane that slides over Layer1, adds a back-navigation bar at the top."
    },
    "ShowFooter": {
      "type": "VARIANT",
      "description": "Whether the footer action area (Cancel + Save buttons) is visible."
    },
    "ShowHelpIcon": {
      "type": "BOOLEAN",
      "default": true,
      "description": "Shows or hides the help (?) icon in the header."
    },
    "Title": {
      "type": "TEXT",
      "default": "Panel Title",
      "description": "Header title text. Injected via data-header-1 in the DOM."
    },
    "_footerButtons": "Footer contains existing Button component instances: 'Cancel' (Primary=No) and 'Save' (Primary=Yes). Override their label by selecting the button on a panel instance and editing its built-in 'x' TEXT property."
  },

  "anatomy": {
    "overlay": "Full-page semi-transparent backdrop behind the container (not part of the component itself; added by .sidepane.is-active)",
    "sidepane-container": {
      "width": 480,
      "borderRadius": 8,
      "marginInlineEnd": 8,
      "shadow": "0px 0px 25px rgba(0,0,0,0.20)",
      "children": {
        "layer2-back-bar": "Only present in Layer=Layer2. Height 40px. Contains back chevron + parent panel title. Lets user navigate back to Layer 1.",
        "header": {
          "height": 55,
          "layout": "HORIZONTAL",
          "children": {
            "header-content": "FILL. Contains title (Bold 15px) and optional description (Regular 12px).",
            "header-icons": "AUTO. Contains help-icon (24×24) and close-icon (24×24)."
          }
        },
        "header-divider": "1px separator between header and body.",
        "body": {
          "height": "FILL (takes remaining space)",
          "padding": "20px all sides",
          "layout": "VERTICAL",
          "description": "Scrollable content area. Insert any content here."
        },
        "footer-divider": "1px separator between body and footer. Only visible when ShowFooter=Yes.",
        "footer": {
          "height": 64,
          "layout": "HORIZONTAL",
          "alignment": "right",
          "visible": "ShowFooter=Yes only",
          "children": {
            "Cancel": "Instance of Button component (Primary=No / secondary stroke style). Label: 'Cancel'.",
            "Save": "Instance of Button component (Primary=Yes / filled blue). Label: 'Save'."
          }
        }
      }
    }
  },

  "tokens": {
    "background": {
      "variable": "ZA/Background/BG-Primary-Default",
      "variableId": "VariableID:575:273",
      "description": "Main panel background (white in Light mode)"
    },
    "footerBackground": {
      "variable": "ZA/Background/BG-Primary-Subtle",
      "variableId": "VariableID:575:275",
      "description": "Footer and Layer2 back-bar background (slightly tinted)"
    },
    "headerDivider": {
      "variable": "ZA/stroke/Stroke 1",
      "variableId": "VariableID:579:41",
      "description": "1px separator lines between header/body/footer"
    },
    "titleText": {
      "variable": "ZA/Text/Text Primary",
      "variableId": "VariableID:575:276",
      "description": "Panel title, close icon, cancel button text"
    },
    "descriptionText": {
      "variable": "ZA/Text/Text Description",
      "variableId": "VariableID:575:277",
      "description": "Subtitle text, body placeholder, back-bar label"
    },
    "primaryButtonFill": {
      "variable": "ZA/Button/Button Fill/Button Primary",
      "variableId": "VariableID:577:38",
      "description": "Save / primary action button background"
    }
  },

  "cssMappings": {
    "--za-sidepane-header-height": "55px",
    "--za-sidepane-footer-height": "64px",
    "--sidepane-bg": "ZA/Background/BG-Primary-Default",
    "--sidepane-footer-bg": "ZA/Background/BG-Primary-Subtle",
    "--sidepane-stroke-color": "ZA/stroke/Stroke 1",
    "--sidepane-overlay": "rgba(0,0,0,0.40)",
    "box-shadow": "0px 0px 25px rgba(0,0,0,0.20)",
    "border-radius": "8px",
    "margin-inline-end": "8px"
  },

  "codeInstantiation": {
    "import": "ZASidePane from '../../component/sidepane/ZASidePane'",
    "usage": {
      "basic": "const pane = new ZASidePane();\npane.show({\n  header1: 'Panel Title',\n  body1: contentElement,\n  footer1: pane.constructFooterEl({ buttonList: [{ name: 'Save', isPrimary: true }, { name: 'Cancel' }] })\n});",
      "withDesc": "pane.show({\n  header1: 'Title',\n  desc1: 'Subtitle or description',\n  body1: contentElement\n});",
      "withLayer2": "// After pane is open, call:\npane.slideOut();\n// Then set body2/footer2:\ncontentElement.querySelector('[data-body-2]').appendChild(layer2Content);"
    }
  },

  "figmaInstantiation": {
    "layer1WithFooter": "const comp = await figma.getNodeByIdAsync('5015:11417');\nconst inst = comp.createInstance();\ninst.setProperties({ 'Title#...': 'My Panel', 'ShowHelpIcon#...': true });\npage.appendChild(inst);",
    "getComponentSet": "const cs = await figma.getNodeByIdAsync('5015:11997');\nconst layer1 = cs.children.find(c => c.name === 'Layer=Layer1, ShowFooter=Yes');\nconst inst = layer1.createInstance();"
  },

  "hardRules": [
    "Panel width is 480px by default. Use 320px / 600px for narrow/wide variants.",
    "Header height MUST be 55px (--za-sidepane-header-height).",
    "Footer height MUST be 64px (--za-sidepane-footer-height).",
    "border-radius MUST be 8px on sidepane-container.",
    "margin-inline-end MUST be 8px (creates the visible gap on the right edge).",
    "Layer2 MUST show a back-navigation bar (40px, back-arrow + parent panel title).",
    "Only use ShowFooter=No when the panel action is triggered elsewhere (e.g. auto-save or read-only).",
    "Never add fills/backgrounds to the header frame itself — leave transparent; colors come from sidepane-container."
  ]
}
